cookiecutter_aws_extensions/__init__.py
cookiecutter_aws_extensions/aws.py
cookiecutter_aws_extensions-0.0.12.dist-info/METADATA
cookiecutter_aws_extensions-0.0.12.dist-info/WHEEL
cookiecutter_aws_extensions-0.0.12.dist-info/top_level.txt
cookiecutter_aws_extensions-0.0.12.dist-info/RECORD
